[
  {
    "productName": "PURELY ELIZ",
    "purchaseDate": "2025.10.06",
    "price": "5.49USD",
    "amount": "1",
    "storeName": "Target",
    "latitude": 33.8583,
    "longitude": -117.7615
  },
  {
    "productName": "CAMPBELLS",
    "purchaseDate": "2025.10.06",
    "price": "1.99USD",
    "amount": "1",
    "storeName": "Target",
    "latitude": 33.8583,
    "longitude": -117.7615
  },
  {
    "productName": "CAMPBELLS",
    "purchaseDate": "2025.10.06",
    "price": "1.99USD",
    "amount": "1",
    "storeName": "Target",
    "latitude": 33.8583,
    "longitude": -117.7615
  },
  {
    "productName": "CAMPBELLS",
    "purchaseDate": "2025.10.06",
    "price": "1.99USD",
    "amount": "1",
    "storeName": "Target",
    "latitude": 33.8583,
    "longitude": -117.7615
  },
  {
    "productName": "CAMPBELLS",
    "purchaseDate": "2025.10.06",
    "price": "1.99USD",
    "amount": "1",
    "storeName": "Target",
    "latitude": 33.8583,
    "longitude": -117.7615
  },
  {
    "productName": "DOLLYPARTONS",
    "purchaseDate": "2025.10.06",
    "price": "4.29USD",
    "amount": "1",
    "storeName": "Target",
    "latitude": 33.8583,
    "longitude": -117.7615
  },
  {
    "productName": "PFCHANG NOOD",
    "purchaseDate": "2025.10.06",
    "price": "4.99USD",
    "amount": "1",
    "storeName": "Target",
    "latitude": 33.8583,
    "longitude": -117.7615
  }
]